wagtailcontentstream/__init__.py
wagtailcontentstream/blocks.py
wagtailcontentstream/models.py
wagtailcontentstream/wagtail_hooks.py
wagtailcontentstream/templates/wagtailcontentstream/blocks/captioned_image.html
wagtailcontentstream/templates/wagtailcontentstream/blocks/heading.html
wagtailcontentstream/templates/wagtailcontentstream/blocks/section_struct_block.html
wagtailcontentstream/tests/__init__.py
wagtailcontentstream/tests/test_models.py
wagtailcontentstream-1.0.0.dist-info/LICENSE
wagtailcontentstream-1.0.0.dist-info/METADATA
wagtailcontentstream-1.0.0.dist-info/WHEEL
wagtailcontentstream-1.0.0.dist-info/top_level.txt
wagtailcontentstream-1.0.0.dist-info/RECORD
