Metadata-Version: 2.1
Name: wagtailcontentstream
Version: 1.0.0
Summary: Wagtail Content Stream provides a StreamField of standard content types.
Home-page: https://github.com/FlipperPA/wagtailcontentstream
Author: Tim Allen
Author-email: tallen@wharton.upenn.edu
License: UNKNOWN
Platform: UNKNOWN
Classifier: Development Status :: 5 - Production/Stable
Classifier: Environment :: Web Environment
Classifier: Intended Audience :: Developers
Classifier: License :: OSI Approved :: BSD License
Classifier: Operating System :: OS Independent
Classifier: Programming Language :: Python :: 3
Classifier: Programming Language :: Python :: 3.7
Classifier: Programming Language :: Python :: 3.8
Classifier: Programming Language :: Python :: 3.9
Classifier: Programming Language :: Python :: 3.10
Classifier: Framework :: Django
Classifier: Framework :: Wagtail
Classifier: Framework :: Wagtail :: 3
Classifier: Topic :: Internet :: WWW/HTTP
Classifier: Topic :: Internet :: WWW/HTTP :: Dynamic Content
Requires-Dist: wagtail (>=3)
Requires-Dist: wagtailcodeblock (>=1.14.0.0)
